c4/__init__.py
c4/exceptions.py
c4/py.typed
c4/compat/__init__.py
c4/compat/strenum.py
c4/diagrams/__init__.py
c4/diagrams/component.py
c4/diagrams/container.py
c4/diagrams/core.py
c4/diagrams/deployment.py
c4/diagrams/dynamic.py
c4/diagrams/system_context.py
c4/renderers/__init__.py
c4/renderers/base.py
c4/renderers/plantuml/__init__.py
c4/renderers/plantuml/backends.py
c4/renderers/plantuml/constants.py
c4/renderers/plantuml/layout_options.py
c4/renderers/plantuml/macros.py
c4/renderers/plantuml/renderer.py
c4_diagrams-0.1.2.dist-info/METADATA
c4_diagrams-0.1.2.dist-info/WHEEL
c4_diagrams-0.1.2.dist-info/licenses/LICENSE
c4_diagrams-0.1.2.dist-info/RECORD
