Metadata-Version: 2.4
Name: c4-diagrams
Version: 0.1.2
Summary: A Python DSL for generating C4 diagrams
Project-URL: Homepage, https://sidorov-as.github.io/c4-diagrams/
Project-URL: Repository, https://github.com/sidorov-as/c4-diagrams
Project-URL: Documentation, https://sidorov-as.github.io/c4-diagrams/
Author-email: Alexey Sidorov <ereon.dev@gmail.com>
License-File: LICENSE
Keywords: python
Classifier: Intended Audience :: Developers
Classifier: Programming Language :: Python
Classifier: Programming Language :: Python :: 3
Classifier: Programming Language :: Python :: 3.10
Classifier: Programming Language :: Python :: 3.11
Classifier: Programming Language :: Python :: 3.12
Classifier: Programming Language :: Python :: 3.13
Classifier: Programming Language :: Python :: 3.14
Classifier: Topic :: Software Development :: Libraries :: Python Modules
Requires-Python: <4.0,>=3.10
Requires-Dist: typing-extensions>=4.15.0
